{
    "maillist": [{
            "company": "ООО \"СКАЙ ИНТЕГРА\"",
            "mail": "info@sky-trade.net",
            "fio": "Чумилин Леонид Александрович"
        },
        {
            "company": "ООО \"Е-ГРУПП\"",
            "mail": "mail@emart.su",
            "fio": "Фесенко Антон Юрьевич"
        },
        {
            "company": "ООО \"Гранд\"",
            "mail": "info@budki.su",
            "fio": "Филиппов Иннокентий Валерьевич"
        },
        {
            "company": "ООО \"ВАЙСКОМ\"",
            "mail": "sales@wiescom.ru",
            "fio": "Алексеева Ксения Юрьевна"
        },
        {
            "company": "ООО \"КСБ\"",
            "mail": "info@ksbmaster.ru",
            "fio": "Мартынов Сергей Георгиевич"
        },
        {
            "company": "ООО \"Технополис\"",
            "mail": "info@tehnopolic.ru",
            "fio": "Шикалов Игорь Иванович"
        },
        {
            "company": "ООО \"АЙРОН-ВЕГА\"",
            "mail": "mail@iron-vega.ru ",
            "fio": "Кобозов Дмитрий Васильевич"
        },
        {
            "company": "ООО \"Аураби\"",
            "mail": "video@aurabi.ru",
            "fio": "Ржевский Антон Викторович"
        },
        {
            "company": "ООО \"Питер\"",
            "mail": "centr@oknapiter.ru",
            "fio": "Калюжный Андрей Александрович"
        },
        {
            "company": "ООО \"ТЕЛЕКАМЕРА\"",
            "mail": "zakaz1@telecamera.ru",
            "fio": "Прищепо Алексей Владимирович"
        },
        {
            "company": "ООО \"Эльтон-Инжиниринг\"",
            "mail": "sale@aliton.ru",
            "fio": "Чупров Михаил Евгеньевич"
        },
        {
            "company": "ООО \"СПЕЦТЕХКОНСАЛТИНГ\"",
            "mail": "sales@pro-spec.ru",
            "fio": "Митрофанов Валерий Анатольевич"
        },
        {
            "company": "ООО «Авангард 18»",
            "mail": "sales@a18pro.ru",
            "fio": "Гужавин Игорь Альбертович"
        }
    ]
}